hapsira/__init__.py
hapsira/bodies.py
hapsira/ephem.py
hapsira/examples.py
hapsira/io.py
hapsira/maneuver.py
hapsira/sensors.py
hapsira/spheroid_location.py
hapsira/util.py
hapsira/warnings.py
hapsira/_math/__init__.py
hapsira/_math/integrate.py
hapsira/_math/interpolate.py
hapsira/_math/ivp.py
hapsira/_math/linalg.py
hapsira/_math/optimize.py
hapsira/_math/special.py
hapsira/constants/__init__.py
hapsira/constants/general.py
hapsira/constants/mean_elements.py
hapsira/constants/rotational_elements.py
hapsira/core/__init__.py
hapsira/core/angles.py
hapsira/core/czml_utils.py
hapsira/core/elements.py
hapsira/core/events.py
hapsira/core/fixed.py
hapsira/core/flybys.py
hapsira/core/iod.py
hapsira/core/maneuver.py
hapsira/core/perturbations.py
hapsira/core/sensors.py
hapsira/core/spheroid_location.py
hapsira/core/util.py
hapsira/core/earth_atmosphere/__init__.py
hapsira/core/earth_atmosphere/jacchia.py
hapsira/core/earth_atmosphere/util.py
hapsira/core/propagation/__init__.py
hapsira/core/propagation/base.py
hapsira/core/propagation/cowell.py
hapsira/core/propagation/danby.py
hapsira/core/propagation/farnocchia.py
hapsira/core/propagation/gooding.py
hapsira/core/propagation/markley.py
hapsira/core/propagation/mikkola.py
hapsira/core/propagation/pimienta.py
hapsira/core/propagation/recseries.py
hapsira/core/propagation/vallado.py
hapsira/core/threebody/__init__.py
hapsira/core/threebody/cr3bp_quantities_calculations.py
hapsira/core/thrust/__init__.py
hapsira/core/thrust/change_a_inc.py
hapsira/core/thrust/change_argp.py
hapsira/core/thrust/change_ecc_inc.py
hapsira/core/thrust/change_ecc_quasioptimal.py
hapsira/czml/__init__.py
hapsira/czml/extract_czml.py
hapsira/earth/__init__.py
hapsira/earth/enums.py
hapsira/earth/util.py
hapsira/earth/atmosphere/__init__.py
hapsira/earth/atmosphere/base.py
hapsira/earth/atmosphere/coesa62.py
hapsira/earth/atmosphere/coesa76.py
hapsira/earth/atmosphere/jacchia.py
hapsira/earth/atmosphere/data/coesa62.dat
hapsira-0.18.0.dist-info/LICENSE
hapsira-0.18.0.dist-info/WHEEL
hapsira-0.18.0.dist-info/METADATA
hapsira-0.18.0.dist-info/RECORD
