Metadata-Version: 2.1
Name: hapsira
Version: 0.18.0
Summary: Utilities and Python wrappers for Orbital Mechanics.
Keywords: aero,aerospace,engineering,astrodynamics,orbits,kepler,orbital mechanics
Author-email: "Sebastian M. Ernst" <ernst@pleiszenburg.de>
Maintainer-email: "Sebastian M. Ernst" <ernst@pleiszenburg.de>
Requires-Python: >=3.8
Classifier: License :: OSI Approved :: MIT License
Classifier: Development Status :: 4 - Beta
Classifier: Intended Audience :: Education
Classifier: Intended Audience :: Science/Research
Classifier: License :: OSI Approved :: MIT License
Classifier: Operating System :: OS Independent
Classifier: Programming Language :: Python
Classifier: Programming Language :: Python :: 3
Classifier: Programming Language :: Python :: 3.8
Classifier: Programming Language :: Python :: 3.9
Classifier: Programming Language :: Python :: 3.10
Classifier: Programming Language :: Python :: 3.11
Classifier: Programming Language :: Python :: Implementation :: CPython
Classifier: Topic :: Scientific/Engineering
Classifier: Topic :: Scientific/Engineering :: Physics
Classifier: Topic :: Scientific/Engineering :: Astronomy
Requires-Dist: astropy
Requires-Dist: astroquery
Requires-Dist: jplephem
Requires-Dist: matplotlib<3.8
Requires-Dist: numba
Requires-Dist: numpy
Requires-Dist: pandas
Requires-Dist: plotly
Requires-Dist: pyerfa
Requires-Dist: scipy
Requires-Dist: czml3 ~=0.5.3 ; extra == "cesium"
Requires-Dist: flit ; extra == "dev"
Requires-Dist: wheel ; extra == "dev"
Requires-Dist: httpx ; extra == "doc"
Requires-Dist: ipython ; extra == "doc"
Requires-Dist: ipykernel ; extra == "doc"
Requires-Dist: ipywidgets ; extra == "doc"
Requires-Dist: jupyter-client ; extra == "doc"
Requires-Dist: jupytext ; extra == "doc"
Requires-Dist: myst-parser ; extra == "doc"
Requires-Dist: nbsphinx ; extra == "doc"
Requires-Dist: nbconvert ; extra == "doc"
Requires-Dist: sgp4 ; extra == "doc"
Requires-Dist: sphinx ; extra == "doc"
Requires-Dist: sphinx-autoapi>=3 ; extra == "doc"
Requires-Dist: sphinx-gallery<=0.7.0 ; extra == "doc"
Requires-Dist: sphinx_rtd_theme ; extra == "doc"
Requires-Dist: sphinx-hoverxref ; extra == "doc"
Requires-Dist: sphinx-notfound-page ; extra == "doc"
Requires-Dist: sphinx-copybutton ; extra == "doc"
Requires-Dist: sphinx-github-role ; extra == "doc"
Requires-Dist: notebook ; extra == "jupyter"
Requires-Dist: ipywidgets>=7.6 ; extra == "jupyter"
Requires-Dist: coverage ; extra == "test"
Requires-Dist: hypothesis ; extra == "test"
Requires-Dist: import-linter[toml] ; extra == "test"
Requires-Dist: mypy ; extra == "test"
Requires-Dist: pre-commit ; extra == "test"
Requires-Dist: pytest ; extra == "test"
Requires-Dist: pytest-cov ; extra == "test"
Requires-Dist: pytest-doctestplus ; extra == "test"
Requires-Dist: pytest-mpl ; extra == "test"
Requires-Dist: pytest-mypy ; extra == "test"
Requires-Dist: pytest-remotedata ; extra == "test"
Requires-Dist: tox ; extra == "test"
Project-URL: Changelog, https://hapsira.readthedocs.io/en/stable/changelog.html
Project-URL: Documentation, https://hapsira.readthedocs.io
Project-URL: Homepage, https://hapsira.readthedocs.io
Project-URL: Source, https://github.com/pleiszenburg/hapsira
Project-URL: Tracker, https://github.com/pleiszenburg/hapsira/issues
Provides-Extra: cesium
Provides-Extra: dev
Provides-Extra: doc
Provides-Extra: jupyter
Provides-Extra: test
